Workbook

Sheet 26
A1: Дата | B1: Приход | C1: Расход | D1: Комментарий | E1: =TODAY()-DATE(YEAR(TODAY()),1,1) -> 96 | F1: Дней с начала года прошло
B2: =SUM(B4:B1061) -> 6802079 | C2: =SUM(C4:C1061) -> 6183007 | E2: =B3/E1 -> 6448.6667 | F2: Средний доход за день
A3: остаток | B3: =B2-C2 -> 619072 | E3: =E2/8 -> 806.08333 | F3: =E3*160 -> 128973.33 | G3: Среднее за час\месяц
A4: 46029 | C4: 15000 | D4: Алишщер и Саид за станок
C5: 10000 | D5: егор за станок
C6: 15000 | D6: антон за станок
C7: 6000 | D7: фрезы
C8: 43920 | D8: аренда
C9: 2000 | D9: фреза
C10: 10900 | D10: электричество дек
B11: 20000 | C11: 20000 | D11: продал печку и отдал егору
C12: 1250 | D12: фреза
A13: 46041 | B13: 5000 | C13: 2000 | D13: балансировка импеллера Игорь
A14: 46048 | B14: 1149999 | C14: 115000 | D14: техновент об
C15: 4060 | D15: резец и фрезы
C16: 2500 | D16: заготовки на проходной элемент клеемазалка
C17: 7040 | D17: проходной элемент клеемазалка
C18: 3490 | D18: латунь на клеемазалку
A19: 46052 | C19: 977500 | D19: техновент об
A20: 46058 | C20: 14500 | D20: электричество янв
A21: 46064 | B21: 50000 | D21: Иван Постников за качалку.
A22: 46067 | B22: 70000 | D22: Ваган за бублик
A23: 46071 | B23: 6000 | D23: ремонт хуйни от дукато
B24: 20000 | C24: 2000 | D24: Цельсий за фланцы
A25: 46077 | C25: 15000 | D25: тумбочка
A26: 46078 | B26: 30100 | C26: 3010 | D26: Цельсий за переходные пластины
A27: 46079 | B27: 10000 | D27: шлифовка ножа
A28: 46083 | B28: 2250000 | C28: =B28*0.1 -> 225000 | D28: технеовент
B29: 40000 | C29: 4000 | D29: акон-техно корпуса 5 шт
C30: 44000 | D30: аренда
C31: 20000 | D31: электричество
C32: 1000 | D32: пруток нержи
A33: 46084 | C33: 36000 | D33: электроиспытания клеемазалки
A34: 46085 | B34: 20000 | C34: 2000 | D34: овен
A35: 46087 | C35: 3500 | D35: оправки БТ40
C36: 1300 | D36: Краеискатель
A37: 46088 | B37: 17000 | D37: Николай радиаторы
C38: 1912500 | D38: техновент об
A39: 46089 | C39: 4000 | D39: какая-то хуйня
A40: 46092 | B40: 54600 | C40: 5460 | D40: акон-техно остаточ за корпуса
B41: 20000 | D41: остаток за тележку под холодильник
C42: 3400 | D42: материал на пальцы для шагпластик
B43: 6600 | C43: 600 | D43: КБ Механика 1 запайщик
A44: 45729 | C44: 7500 | D44: баллон и редуктор на Орехова
C45: 16000 | D45: опрессовщик на орехова
B46: 20000 | D46: резка карбид кремния
B47: 170000 | C47: 17000 | D47: Эконац - 34 планки
A48: 46098 | B48: 6600 | C48: 600 | D48: цельсий
C49: 4944 | D49: всеинстр
C50: 5044 | D50: озон
C51: 1768 | D51: рустам за какие-то штучки
A52: 46099 | C52: 6200 | D52: дробь для песочки
C53: 5000 | D53: аквабласт
A54: 46100 | C54: 3500 | D54: сварка
B55: 8500 | D55: от вовы за сварку
B56: 74500 | C56: 7450 | D56: шагпластик: муфта, пальцы, вал
A57: 46102 | B57: 10000 | D57: обнизил свёрла
B58: 2542180 | C58: 254218 | D58: техновент об
C59: 2160853 | D59: техновент об
A60: 46107 | B60: 6000 | D60: шлифовка планок
B61: 25000 | C61: 2500 | D61: Эдуард (болт на шаут и 2 шестерни)
B62: 10000 | D62: расточка клипонов
A63: 46111 | C63: 14000 | D63: Рустам за воротки
C64: 3000 | D64: Юрий за лампу и прожектор
C65: 8000 | D65: Ростик резка на орехов стенд
B66: 40000 | C66: 4000 | D66: клиновые шайбы и муфты аванс
C67: 7800 | D67: нержавейка на муфты
A68: 46112 | C68: 2800 | D68: провод
C69: 2500 | D69: мелочи
C70: 1700 | D70: металл на проливочный стенд
A71: 46113 | C71: 9000 | D71: металлопласт
C72: 14000 | D72: нутромеры
B73: 33000 | C73: 3300 | D73: Акон-техно, Сергей за цангу
A74: 46115 | B74: 67000 | D74: Стас. Расточка карба и ресивера
B75: 20000 | D75: Максим аванс (из 86000) за шлифовку
A76: 46118 | C76: 44000 | D76: аренда
C77: 6700 | D77: электричество
C78: 29500 | D78: металл на стеллажи.
A79: 46119 | C79: 4000 | D79: приварка штуцеров на опрессовочный
C80: 3200 | D80: пруток нержи и резец
I564: т
I565: т

Sheet 25
A1: Дата | B1: Приход | C1: Расход | D1: Комментарий | E1: 365 | F1: Дней с начала года прошло
B2: =SUM(B4:B1061) -> 30237702 | C2: =SUM(C4:C1061) -> 13443202 | E2: =B3/E1 -> 46012.33 | F2: Средний доход за день
A3: остаток | B3: =B2-C2 -> 16794501 | E3: =E2/8 -> 5751.5413 | F3: =E3*160 -> 920246.61 | G3: Среднее за час\месяц
A4: 45666 | C4: 11860 | D4: прутки
C5: 38200 | D5: аренда дек
C6: 24348 | D6: пневматика на пресс
A7: 45667 | B7: 6600 | C7: 396 | D7: ролик Регат Тайм
C8: 11140.85 | D8: электричество дек.
C9: 11739 | D9: чип и дип
A10: 45672 | C10: 6000 | D10: алишер за помост
C11: 6700 | D11: алюминий на помост
C12: 3500 | D12: всякое
A13: 45675 | B13: 42750 | C13: 2565 | D13: интертекстиль
A14: 45677 | C14: 43000 | D14: наладка чпу
A15: 45678 | C15: 1300 | D15: метчики
B16: 5000 | D16: ваган за маркировку
C17: 5000 | D17: валера аванс за переделку дырок на БХВ
C18: 1000 | D18: смыслов за точилку
A19: 45681 | B19: 25000 | C19: 1500 | D19: эконацпроект за проставочные кольца
C20: 23000 | D20: алёна за резку на гриндер
C21: 2122 | D21: краны на клеемазалку
C22: 935 | D22: сдэк за пневматику
C23: 1070 | D23: сверло т\с
C24: 13500 | D24: Валере за переделку дырок на БХВ
C25: 8700 | D25: ригшеля на гриндер
A26: 45684 | B26: 1054771 | C26: 63287 | D26: Цельсий для юры
B27: 1000000 | C27: 60000 | D27: ТПИ промаванс за хвосты
C28: 4660 | D28: прутки за материал на 2 вала
A29: 45685 | C29: 7500 | D29: валера переделка чайников
C30: 2000 | D30: алишер аванс
C31: 9317 | D31: аванс за метал для эдуарда и на большие железки хвостов
B32: 13000 | C32: 33000 | D32: денис резка на пресс 16мм
C33: 40000 | D33: доплата за металл
C34: 50000 | D34: алёна резка пластин на ТПИ
C35: 9800 | D35: сож
C36: 1500 | D36: хз
A37: 45692 | C37: 8050 | D37: электричество янв
C38: 32800 | D38: аренда дек
C39: 3500 | D39: ваган опоры
C40: 2500 | D40: гайки
C41: 38000 | D41: резка ваган, тпи и на синусную
C42: 3190 | D42: фитинги
C43: 1231 | D43: трубка
A44: 45695 | C44: 2952 | D44: кронштейн монитора
C45: 1152 | D45: кронштейн камеры
C46: 766 | D46: плашка
C47: 809 | D47: метчики
B48: 200000 | C48: 12000 | D48: интертекстиль аванс за бинтомот
B49: 100000 | C49: 6000 | D49: интертекстиль аванс за бинтомот
A50: 45696 | C50: 4950 | D50: присадка
C51: 900 | D51: чехол на шланг
A52: 45698 | C52: 3700 | D52: труба
C53: 6000 | D53: пильные полотна
C54: 3870 | D54: пильные полотна
C55: 19500 | D55: тумбочка
C56: 10000 | D56: разная жбонь
A57: 45700 | C57: 3800 | D57: Юре заготовки
C58: 1500 | D58: два насоса на шлифер
C59: 5500 | D59: пластинки
C60: 917650 | D60: Орехову
C61: 65420 | D61: станок янв.
C62: 575 | D62: мелочёвка
C63: 29000 | D63: мотор на бинтомот
A64: 45703 | C64: 20000 | D64: смыслов
C65: 10000 | D65: алишер
B66: 30000 | C66: 1800 | D66: градусник за переходники
C67: 5430 | D67: корпус фильтра на клеемазку
C68: 1174 | D68: винты
A69: 45706 | C69: 1220
C70: 3667
C71: 1616
C72: 3340
C73: 13005 | D73: пневматика на клеемазалку
C74: 2912
C75: 28242 | D75: шаговик на бинтомот
C76: 1740
A77: 45710 | C77: 10000 | D77: Вова
C78: 10000 | D78: Федя
C79: 60000 | D79: Валера
C80: 7000 | D80: аккум на милку
A81: 45713 | C81: 2500 | D81: лотки под краску
C82: 5000 | D82: вова
C83: 10000 | D83: вытяжка для порошковки
C84: 15130 | D84: краска
A85: 45714 | C85: 15000 | D85: егор за резинки
B86: 104500 | C86: 6270 | D86: Каср шлифовка 19 дисков
B87: 344080 | C87: 20645 | D87: Цельсий для юры
B88: 121800 | C88: 7308
B89: 121800 | C89: 7308
B90: 121800 | C90: 7308
A91: 45716 | C91: 45500 | D91: фильтры, проволока и сож для нитки
A92: 45719 | C92: 14350 | D92: электричество февраль
C93: 38200 | D93: аренда февр
C94: 52370 | D94: пневма на грязнулю.
C95: 5000 | D95: Вова
C96: 12067 | D96: реле на клеемазалку
A97: 45723 | C97: 8000 | D97: трубюа нерж на бинтомот
C98: 10000 | D98: алишщер за напыление
C99: 2000 | D99: метизы
C100: 4154 | D100: мелочи
...

Sheet 24
A1: Дата | B1: Приход | C1: Расход | D1: Комментарий | E1: 365 | F1: Дней с начала года прошло
B2: =SUM(B4:B1040) -> 15229575 | C2: =SUM(C4:C1040) -> 10403067 | E2: =B3/E1 -> 13223.31 | F2: Средний доход за день
A3: остаток | B3: =B2-C2 -> 4826508.2 | E3: =E2/8 -> 1652.9138 | F3: =E3*160 -> 264466.2 | G3: Среднее за час\месяц
A4: 45302 | B4: 4000 | D4: не помню
C5: 20000 | D5: всякой херни напокупал
C6: 17000 | D6: профилометр
C7: 4750 | D7: цанговый патрон и патрон на чпу
C8: 17000 | D8: профилометр
C9: 1750 | D9: резцы
C10: 32800 | D10: аренда
A11: 45303 | B11: 14000 | D11: Магомет ножи
A12: 45306 | B12: 4400 | C12: 264 | D12: ПК Возрождение за штифты
B13: 72400 | C13: 4344 | D13: Синглкап за корпуса шнеков и заточку ножей
B14: 50000 | C14: 3000 | D14: Интертекстиль, модели нижнего стерднего и верхнего этажа
A15: 45307 | B15: 53220 | C15: 3194 | D15: Интертекстиль, модели размотчика и промежуточного этажа и сварку основания
C16: 15000 | D16: Валере за сварку основания
A17: 45311 | B17: 6000 | D17: Олег шлифовка ножей
A18: 45313 | C18: 11238 | D18: переменка декабрь
C19: 88000 | D19: насос для клеемазалки
C20: 37680 | D20: аванс 50% за пневмомал для клеемазалки
C21: 84770 | D21: частотники для клеемазки
C22: 4450 | D22: щуп профилометра
A23: 45314 | B23: 15000 | C23: 900 | D23: Долта за шлифовку ножей
A24: 45316 | C24: 690000 | D24: лазер на клеемазку
C25: 38230 | D25: прутки материал на Долту и бинтомоты
C26: 2200 | D26: полоса в запас
A27: 45317 | B27: 43250 | C27: 2595 | D27: интертекстись бинтомот комплект гнутого железа
C28: 22000 | D28: глазков за комплект на бинтомот
B29: 10000 | C29: 600 | D29: типография за вал
C30: 10000 | D30: доставка лазера
A31: 45322 | B31: 20000 | D31: Вагиф детали для ижа
C32: 1100 | D32: прокладки на компрессор
A33: 45324 | B33: 75400 | C33: 4524 | D33: интертекстиль за детали узла размотки
B34: 5500 | C34: 330 | D34: кофепод за ремонт утюга
C35: 9963 | D35: переменка январь
A36: 45325 | C36: 30000 | D36: валере за мебель на 2 этаж
C37: 65400 | D37: Юре чпу февраль
C38: 3500 | D38: пружины на ТПИ и сверло на бинтомот
A39: 45388 | C39: 750 | D39: деловые за доставку частотников
A40: 45389 | C40: 12500 | D40: столещницы
B41: 15000 | C41: 900 | D41: градусник за фасад кубовки
B42: 54550 | C42: 3273 | D42: интертекстиль
A43: 45330 | B43: 2000 | D43: Эдуард за проточку валов
A44: 45331 | B44: 21900 | C44: 1314 | D44: интертекстиль по 3 счетам
B45: 26180 | C45: 1571
B46: 40570 | C46: 2435
B47: 5500 | C47: 330 | D47: типография за ремонт чего то
B48: 129999.6 | C48: 7800 | D48: Долта за крышки
A49: 45335 | B49: 5000 | C49: 300 | D49: Сергей 2 запайщика
B50: 1349998 | C50: 81000 | D50: ТПИ аванс за 52 СКЦП
A51: 45336 | C51: 9200 | D51: аргон и свар.смесь
C52: 9000 | D52: Илье за настройку принтера
A53: 45337 | C53: 4032 | D53: подшипники на клеемазалку
A54: 45341 | B54: 15000 | D54: вал на какое-то колёсико
C55: 3500 | D55: Иван Бинты, возврат за всякую мелочь
C56: 100000 | D56: аванс за листогиб
A57: 45342 | C57: 2700 | D57: фонарик
C58: 1500 | D58: болты
A59: 45312 | B59: 41000 | C59: 2460 | D59: Интертекстиль бинтомот
B60: 49600 | C60: 2976
C61: 3000 | D61: Паша за печать для Юры
A62: 45345 | B62: 70000 | D62: Андрей Зайкин аванс за руку
A63: 45348 | C63: 540000 | D63: остаток за листогиб
C64: 45000 | D64: доставка и пнр по листогибу
C65: 172160 | D65: мотор редукторы на клеемазку
C66: 2799 | D66: меры шероховатости
A67: 45350 | C67: 27690 | D67: соберизавод профиля на клеемазалку
B68: 104300 | C68: 6258 | D68: СПЛиКОМ за лопаточки (Виталий Рин)
A69: 45352 | C69: 10840 | D69: прутки за металл на лопатки
C70: 72715 | D70: акетон на клеемазалку
C71: 108690 | D71: овен на клеемазалку
C72: 1500 | D72: мастеркам
C73: 12750 | D73: масло в листогиюб
C74: 1750 | D74: образцы шероховат
C75: 12649 | D75: аккумы милвоки
B76: 50000 | D76: Максим за 10 корпусов цилиндрических
A77: 45355 | C77: 47540 | D77: белтпарт ещё 2 моторредуктора на клеемазку
A78: 45356 | B78: 48400 | C78: 2904 | D78: интертекстиль
B79: 104300 | C79: 6258 | D79: СПЛиКОМ остаток
C80: 8400 | D80: лазкову за лазер всякой тестовой ффигни
A81: 45357 | C81: 6377 | D81: электричество февр
B82: 66000 | C82: 3960 | D82: пермь: болты и звёздочки
B83: 10000 | D83: виталий переходные гайки
A84: 45363 | C84: 2000 | D84: матрица
C85: 1000 | D85: матрица
C86: 1800 | D86: лента на пилу
C87: 1832 | D87: ремни и шкивы на клеемазалку
C88: 6200 | D88: детали из 12мм на клеемазалку
C89: 5554 | D89: запрессовочные гайки
C90: 8395 | D90: лебёдка на терминатора
C91: 14000 | D91: электрика на терминатора
A92: 45364 | C92: 249820 | D92: барабаны на конвейеры, подши и т.д.
B93: 1000 | D93: Сапоненко за фигнюшку
A94: 45396 | B94: 25000 | D94: Антон за ремонт йогуртодавилки
C95: 2150 | D95: подши 6005 на клеемазку
C96: 8800 | D96: Глазков детали 6мм на клеемазку
C97: 801 | D97: доставка матрицы
C98: 778 | D98: два штангеля
A99: 45366 | C99: 7870 | D99: доставка мотор редукторов
C100: 250 | D100: серёге за выгрузку
...

Sheet 23
A1: Дата | B1: Приход | C1: Расход | D1: Комментарий | E1: 365 | F1: Дней с начала года прошло
B2: =SUM(B4:B1038) -> 13361210 | C2: =SUM(C4:C1038) -> 7687884.7 | E2: =B3/E1 -> 15543.357 | F2: Средний доход за день
A3: остаток | B3: =B2-C2 -> 5673325.3 | E3: =E2/8 -> 1942.9196 | F3: =E3*160 -> 310867.14 | G3: Среднее за час\месяц
A4: 44938 | B4: 828923 | C4: 49735 | D4: за пенорезку
C5: 5491 | D5: свет за нояб-декаб
C6: 30000 | D6: всякая хрень
C7: 14200 | D7: глазкову за резку Александра, Шайзенверка и ЭССП
B8: 5000 | D8: Вагиф за сварку коллектора и шлифовку проставок
B9: 4000 | D9: олег за завтуливание дизель-генератора
C10: 6500 | D10: прутки ру
A11: 44939 | B11: 12000 | D11: дозаторы для сахара
C12: 1800 | D12: железки с директлота
B13: 2000 | D13: заварил рампу
B14: 3000 | D14: Вагиф за сворку ушка карба
A15: 44941 | B15: 10000 | D15: от александра за шаблоны для токарного
A16: 44942 | B16: 10000 | D16: Илья макаронник за валшестерню
C17: 9500 | D17: спецовка
A18: 44944 | C18: 1000 | D18: паше за помощь
C19: 6000 | D19: направляйки с алика
B20: 12000 | C20: 720 | D20: от Славы за две резалки
A21: 44946 | C21: 7000 | D21: Глазкову за резку на тестя, шайзерверк и синглкап
A22: 44949 | C22: 10000 | D22: Александру за эрозию подшипников для ЭССП и роликов для ИЮМ климат
C23: 10000 | D23: Александру за резьбошлифовку для ЭССП
C24: 150 | D24: развёртка
C25: 1744 | D25: мелочи в ВИ
B26: 35000 | C26: 2100 | D26: Синглкап
B27: 19000 | C27: 1140 | D27: ЮИМ климат два шпонпаза в калёнке +два ролика на иговку
A28: 44950 | B28: 5100 | D28: от фёдора за покраску
C29: 2500 | D29: Валере за покраску фёдора
C30: 16000 | D30: Алёне за резку резины
A31: 44952 | C31: 580000 | D31: эрозия
C32: 13500 | D32: доставка эрозии
C33: 1500 | D33: разгрузка
A34: 270123 | C34: 1092 | D34: подши на вибросито
C35: 5000 | D35: виброопоры
C36: 810 | D36: железки с директлота
C37: 2500 | D37: железки с директлота
B38: 9400 | C38: 564 | D38: СЗС винты и муфточка
A39: 44956 | C39: 4400 | D39: круг на киплайн +латунь на толкатели синглкап +45 на вал кирьянову
B40: 10000 | D40: валшестерня на макароны
C41: 2000 | D41: всякое по мастерской
B42: 3000 | C42: 260 | D42: спет-сервис сварка венчика
B43: 15000 | D43: аванс из 45 на киплайн
A44: 44957 | B44: 45000 | C44: 2700 | D44: киплайн
B45: 26250 | C45: 1575 | D45: кофепод
A46: 44960 | B46: 9000 | C46: 540 | D46: кофепод за ремонт трёх утюгов
B47: 50000 | D47: Кирьянов, аванс за вибросито
C48: 12000 | D48: Александр за обучение на эрозии
C49: 19500 | D49: Глазков, резка на вибросито
A50: 44962 | C50: 11219 | D50: всякое во всеинстр
A51: 44964 | C51: 7000 | D51: Александр эрозия на Киплайн
A52: 44965 | B52: 10000 | D52: Илья макаронник за шестерню 43 зуба и слесарные работы
C53: 5700 | D53: линейка на токарник
A54: 44970 | C54: 300000 | D54: круглошлиф
C55: 12500 | D55: железки всякие
C56: 25000 | D56: ремонт сварочника
C57: 10000 | D57: электрика
B58: 44000 | C58: 2640 | D58: СЗС за 12 дисков
A59: 44972 | C59: 3000 | D59: паша за 3 дня
C60: 1000 | D60: всеинстр
B61: 4000 | D61: какая-то штучка для велосипедика
A62: 44973 | B62: 46000 | C62: 2760 | D62: синглкап за ремонт 6 утюгов и 32 толкателя
A63: 44974 | B63: 6000 | C63: 180 | D63: Киплайн доплата за пневмолягушку
B64: 68425 | C64: 4106 | D64: ЭССП окончатеьный расчет
A65: 44977 | C65: 2500 | D65: всеинстр
B66: 3500 | D66: кирьянов, шлифовка ножа
B67: 2000 | D67: Антон металлург за сварку
C68: 3000 | D68: Егору за помощь
A69: 44978 | C69: 15000 | D69: Валере за кубик кирьянову
A70: 44979 | C70: 3500 | D70: проволока на эрозию
C71: 2059 | D71: токосъёмники для эрозии
B72: 15000 | D72: Вадим аванс за 2 шестерни из 20000
B73: 31600 | C73: 2212 | D73: 330ОМ за 4 кронштейна
A74: 44983 | B74: 10000 | D74: Вадим за 3 шестерни
C75: 3900 | D75: проволока на эрозию
C76: 1000 | D76: доставка проволоки
C77: 4000 | D77: проволока на эрозию
A78: 44984 | C78: 5300 | D78: патрон на токарный
C79: 318 | D79: ВИ
C80: 330 | D80: авито
A81: 44986 | B81: 10000 | D81: Фёдор за пастину
B82: 16200 | C82: 972 | D82: синглкап за шифовку корпуса шнека +4 направляющих +переходники
B83: 27000 | C83: 1620 | D83: Цельсий проф за 3 пронштейна +пульт
C84: 1500 | D84: ВИ
C85: 2500 | D85: фильтр СОЖ на эрозию
B86: 60000 | D86: Кирьянов за роторные ножи
C87: 7500 | D87: Глазков за резку уголковФдору, и за железо на стенд балансировочный и эрощию
A88: 44987 | C88: 9300 | D88: электричество янв-февр
B89: 17000 | D89: аванс за резку листа
A90: 44988 | B90: 6500 | D90: остаток за резку
C91: 17000 | D91: глазкову за резку листа
C92: 32000 | D92: валере за тумбочку и покраску консолей
B93: 575621 | C93: 40293 | D93: Цельсий
C94: 500790 | D94: Юре
A95: 44992 | C95: 2600 | D95: всякая хрень
C96: 2800 | D96: глазкову за резку 2 ножей к чудолопате и эксцентриков на вибросито
A97: 44993 | C97: 3000 | D97: Егору за помощь
A98: 44998 | B98: 3000 | D98: от Ильи макаронника за шлифовку валика
C99: 5200 | D99: КМ4-планшайба
A100: 45000 | C100: 2600 | D100: прутки ру
...

Sheet 22
A1: Дата | B1: Приход | C1: Расход | D1: Комментарий | E1: 365 | F1: Дней с начала года прошло
B2: =SUM(B4:B2152) -> 10224884 | C2: =SUM(C4:C2152) -> 6327440.5 | E2: =B3/E1 -> 10677.926 | F2: Средний доход за день
A3: остаток | B3: =B2-C2 -> 3897443.1 | E3: =E2/8 -> 1334.7408 | F3: =E3*160 -> 213558.53 | G3: Среднее за час\месяц
A4: 44564 | C4: 10000 | D4: Глазкову за вал
A5: 44567 | C5: 2000 | D5: Валере за покрасту подтумбочек мистер дорс
C6: 2000 | D6: всякая мелочь
B7: 6000 | D7: проточка валов
A8: 44206 | C8: 600 | D8: шлифдиски на плоскошлиф
C9: 6000 | D9: песочка ракет
C10: 2000 | D10: фрещза
A11: 44207 | B11: 20500 | D11: от Кирьянова за корпус намотчика, трубу намотчика и проточку трубы кристаллизатора
A12: 44208 | B12: 10000 | D12: от кирьянова аванс за раму
B13: 2000 | D13: шайбы регулировочные
A14: 44209 | B14: 2000 | D14: фрезеровка каикх-то карманов
B15: 20000 | D15: от Юры за аренду январь
C16: 40386 | D16: аренда янв
C17: 2460 | D17: электричество декабрь.
A18: 44575 | B18: 3000 | D18: Кирьянов проточка трубы +барабанчик для свинца
B19: 20000 | D19: Ольховский промаванс за ракеты
C20: 1600 | D20: 123 блоки
A21: 44576 | C21: 6500 | D21: Ольховский матовая палка
C22: 6000 | D22: Валере за покраску ракет
A23: 44580 | C23: 558 | D23: краска на ракеты
C24: 57 | D24: гайки
C25: 7777 | D25: клёпки на ракеты, шланг на плоскошлиф, лампы для плоскошлифа
A26: 44581 | C26: 2440 | D26: электрофигня на ракеты
C27: 700 | D27: Гохе за шлифдиски
A28: 44582 | B28: 1600 | D28: сварил кастрюлю
C29: 7500 | D29: Глазкову за резку на Кирьянова и Александра
B30: 66000 | D30: о Ольховского за ракеты
A31: 44584 | B31: 8000 | D31: от Александра за штурвальчик и два болта,
B32: 1600 | D32: сварил батут
B33: 2200 | D33: ремонт конуса Глеб
C34: 132 | D34: налог
B35: 1600 | D35: сварил коляску
A36: 44588 | C36: 3570 | D36: железо из прутков
C37: 170 | D37: свёрла
A38: 44589 | B38: 40000 | D38: Павел аванс за козырёк из 54К
A39: 44590 | B39: 25000 | D39: Кирьянов ремонт головки кристаллизатора
A40: 44591 | C40: 8500 | D40: угловая приставка
A41: 44593 | C41: 20000 | D41: Глазков за резку жетонов Ольховского, жетонов радиста, пульта на плоскошлиф и железа на Кирьянова и на козырёк нержа
A42: 44594 | C42: 7500 | D42: Глазков за сварку полубублика Александру
B43: 2000 | D43: сварка генератора военным
B44: 2000 | D44: ремонт вала куры гриль
C45: 5334 | D45: Альберту за трубу на козырёк
C46: 6000 | D46: Валера покраска Кирьянова и козырька
A47: 44600 | B47: 14000 | D47: остаток за козырёк
A48: 44601 | C48: 1400 | D48: доставка магнитной плиты из Белки
B49: 3000 | D49: от Серёги за нож полиграфический на листогиб
B50: 2000 | D50: от Макса за 2 шаблона
B51: 20000 | D51: Юра, аренда февр
C52: 39500 | D52: аренда февр
C53: 4800 | D53: Глазков, шаблоны Максу, напил на Геркулес
A54: 44603 | B54: 5000 | D54: Ласткап ремонт шнека
C55: 380 | D55: налог
C56: 740 | D56: доставка подноса на токарный
C57: 600 | D57: цепочки для медальонов Ольховского
C58: 1000 | D58: доставка цепочек
B59: 16000 | D59: от Саши за сварку оградки бублика
B60: 21000 | D60: от Кирилла за 26 упоров и 2 планки
C61: 1260 | D61: налог
A62: 44606 | B62: 19000 | D62: от Кирьянова за болты и гайки
C63: 4800 | D63: балллон под пропан
C64: 650 | D64: заправка пропана
A65: 44612 | B65: 2000 | D65: сварка барабана стиралки
A66: 44613 | B66: 2500 | D66: Кирьянов грибок центровочный
C67: 2800 | D67: нержа на грипсы
A68: 44614 | B68: 15000 | D68: Константин аванс из 50 за проектирование мебели
A69: 44615 | B69: 5000 | D69: за грипсы
A70: 44617 | B70: 8250 | D70: от Кирилла типография за вал
C71: 495 | D71: алог
B72: 30000 | D72: Ольховский за медальоны
B73: 150000 | D73: Градус аванс за холодилку Геркулес
C74: 9000 | D74: налог
A75: 44619 | B75: 1500 | D75: сварка барабана стиралки ещё раз
B76: 1600 | D76: проточка торм дисков
A77: 44620 | C77: 25000 | D77: валере за лист 3мм нерж
A78: 44621 | B78: 1600 | D78: сварка крюка
B79: 30000 | D79: от Фёдора за подставку из нержи
C80: 8600 | D80: Альберту за трубу для Паши
A81: 44622 | C81: 38200 | D81: аренда март
C82: 1750 | D82: болты типография, гайки, шлифдиски
C83: 480 | D83: петли на электрошкаф Кирьянов
A84: 44623 | C84: 1500 | D84: болты на Кирьянова, стрейч
A85: 44624 | C85: 2800 | D85: болты нерж на вентиляторы
C86: 500 | D86: болты в асс.
B87: 9900 | D87: Андрей за пальцы для рохли
C88: 597 | D88: налог
C89: 1200 | D89: электричество февраль
A90: 44625 | B90: 2000000 | D90: аванс за детекторы
C91: 120000 | D91: налог
A92: 44626 | B92: 18400 | D92: от Паши за струбцины
C93: 79000 | D93: строгальник
A94: 44628 | B94: 35000 | D94: от Кости за проект мебели
A95: 44629 | B95: 4000 | D95: от Михаила за направляющие
A96: 44630 | B96: 2000 | D96: от Михаила за направлябщие
C97: 34286 | D97: хомуты на ДФУ
A98: 44632 | B98: 10000 | D98: от Александра за 2 подставки для тумбочек
C99: 600 | D99: налог
C100: 1400 | D100: Глазкову за резку под тумбочки
...

Sheet 21
A1: Дата | B1: Приход | C1: Расход | D1: Комментарий | E1: 365 | F1: Дней с начала года прошло
B2: =SUM(B4:B2143) -> 4818296 | C2: =SUM(C4:C2143) -> 2491250.8 | E2: =B3/E1 -> 6375.4664 | F2: Средний доход за день
A3: остаток | B3: =B2-C2 -> 2327045.2 | E3: =E2/8 -> 796.9333 | F3: =E3*160 -> 127509.33 | G3: Среднее за час\месяц
A4: 44201 | B4: 5000 | D4: рассверлил Вепрю раму
B5: 2000 | D5: работы по прикладу Вепрь
B6: 10000 | D6: от Кмузова аванс за кресла (по 3500 штука)
A7: 44202 | C7: 1640 | D7: металл на зиговку
A8: 44208 | C8: 6500 | D8: валы на зиговку
C9: 8400 | D9: частотник на зиговку
A10: 44209 | B10: 15000 | D10: от Александра за подтумбочки мр.Дорс. 7250 х 6шт = 43500
C11: 3600 | D11: Антону за овальную трубу для Кмузова
B12: 1700 | D12: сварил кусок инвколяски
A13: 44210 | C13: 13300 | D13: распил на Зиговку, пульт Орехову, проушины на сидения Кмузову, мистердорс
A14: 44211 | C14: 260 | D14: метизы на сиденья Кмузову
C15: 2600 | D15: электрошкаф на чпу
A16: 44213 | C16: 5650 | D16: блоки питания на ЧПУшку
C17: 1300 | D17: электромелочь на ЧПУшку
C18: 250 | D18: винты на кресла Кмузова
B19: 10000 | D19: от Кмузова за кресла (2500 должен)
A20: 44214 | B20: 15000 | D20: от Ольховского аванс за бабочки и ключи
C21: 480 | D21: электрика в щит ЧПУ
A22: 44215 | B22: 5000 | D22: от кмузова, должен ещё 1500
C23: 4500 | D23: труба на подтумбочники мистер дорс
A24: 44216 | C24: 20500 | D24: Алёне за резку бабочек и ключей для Ользовского
C25: 3600 | D25: Антону за трубу для мистердорс
A26: 44217 | B26: 45000 | D26: Гроссххолод зха сборку щитов
C27: 2700 | D27: налрг за гроссхолод
A28: 44223 | B28: 10000 | D28: от Огнева за кроны
C29: 10000 | D29: лазер на ключи Ольховскому
A30: 44224 | C30: 10000 | D30: Валере за покраску подтумбочников
B31: 2000 | D31: сварка нержавки
A32: 44227 | C32: 4650 | D32: метчики
C33: 5000 | D33: Валере за покраску Огневу кронштейнов
C34: 6300 | D34: Глазкову за резку кронштейнов для огнева
A35: 44228 | B35: 105000 | D35: от Ольховского за Лунтиков и 12 ключей
A36: 44230 | B36: 26000 | D36: от огнева за кроны
A37: 44234 | C37: 2000 | D37: покраска зиговки
C38: 400 | D38: пружины на зиговку
C39: 250 | D39: метизы на зиговку
A40: 44235 | C40: 1000 | D40: Феде за помощь
B41: 11825 | D41: Русхим за предметные столики
C42: 827.75 | D42: налог за русхим
A43: 44236 | B43: 28500 | D43: от Александра за подтумбочки мр.Дорс. 7250 х 6шт = 43500
A44: 44237 | C44: 30400 | D44: шринкер
A45: 44238 | B45: 1880 | D45: от Лобастова за шпильки.
A46: 44240 | C46: 3585 | D46: за редуктор
B47: 10000 | D47: от Михаила за сварку телеги и переборку валов для станка
A48: 44242 | C48: 4000 | D48: Антону за лист алюминия
C49: 4119 | D49: шлифкруги
A50: 44244 | B50: 100000 | D50: от Ольховского аванс за конешкаф и ирис
A51: 44245 | C51: 3674 | D51: молотки и прощее для листовухи
C52: 1587 | D52: заклёпки
C53: 5400 | D53: Антону за уголок на конешкаф
A54: 44246 | C54: 11760 | D54: колёса для конешкафа
C55: 4560 | D55: петли для конешкафа
A56: 44250 | C56: 2398 | D56: сварочная проволока
A57: 44252 | C57: 5775 | D57: замок для конешкафа
A58: 44253 | C58: 2640 | D58: заклёпки для конешкафа
C59: 4555 | D59: выдвигалки для конешкафа
A60: 44255 | C60: 8300 | D60: мотор редуктор для зиговки
C61: 680 | D61: микрометр
B62: 140000 | D62: от Орехова за основание горелок +Юрины деньги
C63: 9800 | D63: налог за Ореховые дениьги
C64: 111600 | D64: Юрины деньги +Юрина доляна за основание горелок
A65: 44257 | C65: 770 | D65: доставка завка из Ростова
C66: 20500 | D66: алюминий для конешкафа
A67: 44261 | C67: 3000 | D67: резец и пластины
C68: 26000 | D68: Глазков резка и гибка каркаса на конешкаф
B69: 15320 | D69: от Игоря за работу над камином
B70: 8900 | D70: от Игоря аванс 50% за второй прототип камина
A71: 44265 | C71: 550 | D71: метизы
C72: 1100 | D72: доставка мотора для зиговки
B73: 39300 | D73: детекторы упячек
C74: 2751 | D74: налог за детекторы
A75: 44266 | C75: 16500 | D75: Сергею за резку обшивки конешкафа
B76: 8900 | D76: от Игоря остаток за второй камин
C77: 3312 | D77: налог за бабло от Игоря
B78: 1500 | D78: от Дэн Савченко за четыре пластины (всего 4000)
A79: 44269 | B79: 2000 | D79: за сварку коляски
B80: 2500 | D80: от Дэн Савченко за четыре пластины (всего 4000)
A81: 44270 | C81: 1500 | D81: заклёпки
C82: 900 | D82: нерж трубка
A83: 44271 | B83: 9000 | D83: от Шнитко за шкаф
C84: 7500 | D84: Паше за шкаф
A85: 44274 | C85: 300 | D85: краска чёрная
C86: 6200 | D86: Юре актуатор
C87: 2100 | D87: Антону за лист 0,5 нержи
A88: 44275 | C88: 800 | D88: сгоны из нержи
B89: 1500 | D89: проточил какую-то фигню
A90: 43912 | C90: 500 | D90: Феде за помощь
B91: 100000 | D91: от Ольховского промежуточный аванс
C92: 1000 | D92: резец под шифер
A93: 44278 | C93: 850 | D93: винты на колёса нерж
C94: 4000 | D94: алюм 1,5мм
C95: 12000 | D95: алюм 3мм
C96: 1000 | D96: нерж труба для орехова
C97: 500 | D97: доставка
A98: 44280 | C98: 11500 | D98: резка и гибка алюмина на конешкаф
C99: 7400 | D99: резка и гибка Юре управления акселлератором
C100: 4000 | D100: разное всякое гибка и резка
...

Sheet 20
A1: Дата | B1: Приход | C1: Расход | D1: Комментарий | E1: 365 | F1: Дней с начала года прошло
B2: =SUM(B4:B2131) -> 3509497 | C2: =SUM(C4:C2131) -> 1735936.4 | E2: =B3/E1 -> 4859.0701 | F2: Средний доход за день
A3: остаток | B3: =B2-C2 -> 1773560.6 | E3: =E2/8 -> 607.38377 | F3: =E3*160 -> 97181.403 | G3: Среднее за час\месяц
A4: 43836 | C4: 3900 | D4: алюминий на шкив
C5: 3700 | D5: фанера дэну
A6: 43844 | B6: 35000 | D6: от Ольховского аванс за верстак 50%
B7: 15000 | D7: от Ебобата аванс за стеллаж (из 35)
A8: 43845 | C8: 15000 | D8: Валере аванс за верстак и Ебобата, общ 25+20
A9: 43845 | B9: 7000 | D9: от Михалыча за железяки
C10: 7000 | D10: Ане за железяки
A11: 43483 | B11: 27000 | D11: от Юры за кроны вентиляторов для орехова
C12: 3500 | D12: всякая хрень с Алика
A13: 43850 | B13: 1500 | D13: от дэна за хранение железяк
C14: 4000 | D14: Ане за резку уголков для Ебобата и переделку Зигиных нащельников
A15: 43851 | C15: 3000 | D15: Валере за покраску пёськи и Зигиных нащельников
C16: 8500 | D16: галтовочные тела
C17: 2500 | D17: шлифдиски всякие
A18: 43487 | C18: 10544 | D18: направляйки для ЧПУ
B19: 3000 | D19: от Вовы за покраску пёськи
A20: 43854 | C20: 10000 | D20: Валере остаток за стеллаж Ебобата
A21: 43856 | B21: 20000 | D21: от Ебобата за стеллаж. Расчитался.
C22: 4000 | D22: всякая хрень с Алика
A23: 43857 | B23: 10000 | D23: от Ольховского аванс на болты и гайки из чугуна
C24: 10400 | D24: за чугун для Ольховского
B25: 15000 | D25: от Кирьянова аванс за станок (из 60)
A26: 43861 | C26: 20000 | D26: за лазер на станок Кирьянова и удлинители сварстола
B27: 3000 | D27: от Сорокина за удлинители сварстола
B28: 41000 | D28: за изготовление оснований испытательных для Славы
A29: 43864 | C29: 3084 | D29: ленты для пилы
C30: 850 | D30: всякая мелочёвка для намоточного станка
C31: 20000 | D31: металл за основания стендов для Славы
C32: 500 | D32: разгрузка металла
A33: 43870 | C33: 2500 | D33: Михаоыч
A34: 43871 | B34: 26500 | D34: от Ольховского за болванку из меди и на тиски\гриндер
C35: 16000 | D35: Антону за медь
B36: 1200 | D36: сварка вилки велика
C37: 10450 | D37: тиски и гриндер
A38: 43872 | C38: 20800 | D38: Валере за верстак Ольховского
A39: 43876 | B39: 39900 | D39: От Ольховского остатовк за верстак
B40: 4600 | D40: от Ольховского за электрику
C41: 4600 | D41: электрика на верстак
C42: 159 | D42: длинное сверло для Кирьянова
C43: 12000 | D43: ТО и ремонт станков
C44: 3500 | D44: масло на станки
C45: 1750 | D45: ремни на намоточный станок
A46: 43878 | B46: 1200 | D46: от Кирьянова за пиптик
A47: 43879 | C47: 37274.4 | D47: металл на орен
C48: 19 | D48: платёжка
A49: 43881 | C49: 450 | D49: диски 230
C50: 500 | D50: трубка 8х1
C51: 1000 | D51: разгрузка металла
A52: 43882 | C52: 2500 | D52: михалыч
A53: 43886 | C53: 2500 | D53: Рябову за гравировку болтов
A54: 43889 | B54: 50000 | D54: ост за болты Ольховский
A55: 43891 | C55: 2500 | D55: центроискатель оптический
C56: 700 | D56: резец
C57: 3000 | D57: пуансоны центрдрилл
C58: 440 | D58: олеиновая кислота и сало для резьб
A59: 43892 | C59: 5250 | D59: резка шестёрки на Орен
B60: 5000 | D60: за орен
C61: 300 | D61: разгрузка хер знает чего
C62: 424 | D62: замок на сарай
A63: 43894 | C63: 500 | D63: переноска компрессоров
C64: 15000 | D64: аренда сарая
A65: 43896 | C65: 500 | D65: разгрузка меди
A66: 43899 | C66: 1500 | D66: Максу за помощь с намоточником
B67: 50000 | D67: за Орен
A68: 43906 | C68: 6000 | D68: Валере за покркаску намоточника
B69: 50000 | D69: от Сергея за намоточник
C70: 5900 | D70: серва для ТВ16
C71: 5200 | D71: длинная горелка +отрезные диски
A72: 43913 | B72: 55000 | D72: от Актуария окэшили с сервиса 110
A73: 43914 | C73: 20000 | D73: Валере в подотчёт
A74: 43915 | B74: 4000 | D74: от Сорокина за его железки
C75: 30000 | D75: нарезка на орен, сорокину и тв-16
B76: 5000 | D76: от горыныча за расширитель сомоката
C77: 8700 | D77: за хомуты для детекторов
B78: 48501 | D78: аванс 30% за детекторы
A79: 43930 | C79: 8000 | D79: Валере за рамы. Рассчитались
C80: 650 | D80: Антону за трубку
A81: 43934 | C81: 3000 | D81: Максу за хомуты
B82: 10000 | D82: от Славы за Мытищи
A83: 43935 | C83: 10250 | D83: Сорокину за хомуты
A84: 43939 | C84: 13000 | D84: Паше за маркировку пультов для Орена и резку деревяшек на подставки
A85: 43940 | B85: 70000 | D85: от Юры за сборку Орена
A86: 43942 | B86: 62582 | D86: отСлавы за хомуты
A87: 43946 | C87: 4500 | D87: оезка деталей для такелажных тележек
A88: 43947 | C88: 3000 | D88: Михалычу
A89: 43951 | B89: 46800 | D89: за кран от Цельсия
C90: 7000 | D90: металл на кран Цельсия
C91: 10000 | D91: Валере за сварку крана
C92: 3450 | D92: патрон сверлильный для гнома
A93: 43922 | B93: 6000 | D93: от никиты за пряжку
A94: 43958 | B94: 47000 | D94: от Славы за хомуты.
B95: 18600 | D95: от Славы аванс за мытищи
B96: 1500 | D96: аванс за прягу от Ярослава Бучковского
A97: 43959 | C97: 1500 | D97: Антону за калиброванный пруток Ф20
C98: 5600 | D98: Валере за металл на краник
C99: 8390 | D99: михалычу за мытищи
C100: 14000 | D100: Максу за мытищи
...

Sheet 19
A1: Дата | B1: Приход | C1: Расход | D1: Комментарий | E1: 365 | F1: Дней с начала года прошло
B2: =SUM(B4:B2125) -> 3540824 | C2: =SUM(C4:C2125) -> 1839484 | E2: =B3/E1 -> 4661.2055 | F2: Средний доход за день
A3: остаток | B3: =B2-C2 -> 1701340 | E3: =E2/8 -> 582.65068 | F3: =E3*160 -> 93224.11 | G3: Среднее за час\месяц
A4: 43466 | C4: 12500 | D4: делительная головка
C5: 840 | D5: доставка головки
C6: 4000 | D6: милвоки
B7: 15000 | D7: сварка рамы для Юры
A8: 43477 | C8: 660 | D8: крепмаркет
C9: 2055 | D9: литые кроны
B10: 10000 | D10: аванс за "паровоз"
C11: 6200 | D11: аренда и электричество
C12: 300 | D12: фрезы
C13: 1400 | D13: фрезы
A14: 43480 | C14: 1500 | D14: МКЭШ
C15: 700 | D15: латунные болты
A16: 43482 | B16: 6000 | D16: за рельсодержатель
C17: 632 | D17: чугунина
C18: 883 | D18: опрыскиватель, угольник, маслёнка
C19: 674 | D19: краска для рамочки
A20: 43485 | B20: 5000 | D20: от Павла за парогенератор
C21: 2500 | D21: Юре за парогенер
B22: 10000 | D22: от Юры за сборку Воронежа
B23: 57600 | D23: от Галины за подставки для туббочек
C24: 5200 | D24: металл на подставки
A25: 43127 | C25: 1350 | D25: проволока
A26: 43493 | C26: 6130 | D26: рельсы
A27: 43494 | B27: 2000 | D27: от Кмузова за рельсодержатель
A28: 43495 | C28: 5500 | D28: термосвёрла
A29: 43497 | B29: 10000 | D29: Максим аванс за стол
A30: 43500 | B30: 5000 | D30: от МР за снег
C31: 6000 | D31: Юре за аренду
C32: 7300 | D32: деревяшки для стола
B33: 5000 | D33: Роман аванс за турник
A34: 43502 | B34: 20000 | D34: Евгений за рамку, рассчиталсчя полностью
C35: 5300 | D35: металл для Романа и Максима
C36: 1000 | D36: латунные болты для рамки
A37: 43506 | C37: 900 | D37: абразивные круги
C38: 300 | D38: присадочные прутки
C39: 430 | D39: стремянка от ЗиЛ
A40: 43507 | C40: 2250 | D40: кольцевая фреза и борфреза
A41: 43509 | C41: 1600 | D41: покраска стола
C42: 13000 | D42: резка лазером для Макса и домино
B43: 15000 | D43: от Юры за сварку рамы Пламя
A44: 43510 | C44: 2250 | D44: болты для подставок Ямаха + мелочи в мастерскую.
B45: 20000 | D45: от Макса предоплата за 4 мотодержалки
C46: 1200 | D46: резка и шлифовка плиты для 3дпринтера
A47: 43511 | B47: 10000 | D47: от Евгения аванс за домино
C48: 3000 | D48: покраска турника
A49: 43512 | B49: 15000 | D49: Роман ост. За турник
B50: 2500 | D50: роман за доставку турника
A51: 43513 | C51: 2240 | D51: леруа, материалы для стола и турника
A52: 43515 | C52: 370 | D52: сверло центровочное
A53: 43516 | B53: 17500 | D53: от Юры за сборку Пламя
B54: 13000 | D54: стол+подоконник окончательны расчёт
A55: 43517 | B55: 11890 | D55: за панели для РЭА
C56: 832 | D56: налог за панельки
C57: 5000 | D57: за изготовление панелей Анне
B58: 2000 | D58: от Кмузова за хранение его барахла
A59: 43520 | B59: 2000 | D59: от Романа за скобы
B60: 5000 | D60: от Вячеслава Струка за вторую плиту на принтер
C61: 2000 | D61: Юре за алюминий для плиты
B62: 10000 | D62: предоплата за дверки шкафа (всего 17 500)
B63: 1500 | D63: заварил коляску
A64: 43522 | B64: 7500 | D64: за дверки шкафа. Полностью
A65: 43523 | C65: 2660 | D65: метчик м2,5, метчикодержатель, винтики
B66: 2500 | D66: Евгений за доминошки промаванс.
A67: 43524 | C67: 6000 | D67: Юре за аренду
A68: 43525 | B68: 5000 | D68: от Романыча за снег
A69: 43526 | B69: 1000 | D69: предоплата за увеличение стула и проставки
A70: 43527 | C70: 1282 | D70: метчик м8
B71: 60000 | D71: пришло за мотоподставки Ямаха
C72: 4200 | D72: отложил на налох
C73: 18600 | D73: Максу доляна за мотоподставки
B74: 2500 | D74: доплата за увеличение стула и проставки, полностью закрыто
A75: 43529 | C75: 5500 | D75: резка заготовок для табуретки
A76: 43530 | C76: 750 | D76: колёсики для табуретки
C77: 900 | D77: колёсики для табуретки
A78: 43531 | B78: 20000 | D78: от Евгения за табуретку (итого пришло 30К +2500 на пиво, полностью закрыто, доминошки пока без аванса)
C79: 1000 | D79: покраска табуретки
C80: 5000 | D80: аванс за воронение доминошек
C81: 348 | D81: болты для табуретки
C82: 1100 | D82: электричество за февр
A83: 43533 | C83: 1700 | D83: мелочёвка в мастерскую
A84: 43537 | B84: 22500 | D84: Евгений за 9 семигранных гаек (полностью закрыл)
C85: 2000 | D85: лазерная гравировка
C86: 5000 | D86: Вове за куски табуретки
C87: 1500 | D87: цепь + бита Милвоки
A88: 43539 | B88: 7000 | D88: от Романа за проставки для турника
C89: 1000 | D89: покраска проставок для турника
C90: 8700 | D90: химия
A91: 43540 | C91: 1500 | D91: металл по мастерской
A92: 43542 | C92: 3287 | D92: шлифовочная расходка
C93: 9600 | D93: милкошлифка
A94: 43544 | B94: 5000 | D94: Кмузов за бетонодавилку
A95: 43545 | B95: 3500 | D95: Слава за фрезерование стола для принтера
C96: 11000 | D96: чугун
C97: 1600 | D97: петли для доминошек
A98: 43547 | C98: 460 | D98: бур для бетонодавилки
C99: 13600 | D99: окончательная оплата за воронение доминошек
C100: 5000 | D100: Михалычу за доминошки
...

Sheet 18
A1: Дата | B1: Приход | C1: Расход | D1: Комментарий | F1: б\н Юра
B2: =SUM(B4:B2110) -> 1031550 | C2: =SUM(C4:C2110) -> 535506
A3: остаток | B3: =B2-C2 -> 496044
A4: 43107 | B4: 10000 | D4: предоплата за кабельные стеллажи
A5: 43111 | B5: 1500 | D5: предоплата за 3 волшебные палки
A6: 43114 | B6: 3000 | D6: сварка рамы велосипеда
A7: 43115 | B7: 1500 | D7: ост за 3 палочки
A8: 43115 | B8: 500 | D8: ост. За палочки перед НГ
A9: 43117 | B9: 2000 | D9: предоплата за кашпо
A10: 43121 | B10: 5000 | D10: кронштейны в гараж
A11: 43128 | B11: 5500 | D11: ост за кашпо
A12: 43132 | C12: 3500 | D12: диск по металлу 305
C13: 1360 | D13: фреза Ф8 по алюминию
B14: 4500 | D14: предоплата для сварки швеллера для ванной
C15: 4000 | D15: алюминиевый уголок 80х40х3 для сварки швеллера
A16: 43134 | C16: 6000 | D16: ЛДСП и фурнитура для стеллажей кабельных
B17: 2000 | D17: за фрезеровку крышки от компа
A18: 42772 | B18: 4500 | D18: сварка швеллера алюминиевого.
C19: 3700 | D19: фрезы Олмитул
A20: 42773 | C20: 2100 | D20: фанера на катушки
C21: 1600 | D21: металл Дэнчику на кронштейны
A22: 42774 | C22: 2500 | D22: лаки и краски всякие
C23: 400 | D23: лиственница на птичьи домики
B24: 1500 | D24: аванс на два скворешника
C25: 1900 | D25: фанера на катушки
A26: 43141 | B26: 5000 | D26: кронштейны и длинные хреновины Дэнчику
A27: 43143 | B27: 1500 | D27: оплата за два скворешника
B28: 1000 | D28: аванс за ключи
A29: 43148 | B29: 35000 | D29: оплата за стеллажи кабельные
C30: 250 | D30: железо (пруток и полоса)
A31: 43149 | B31: 4000 | D31: остаток за ключи
A32: 43153 | B32: 11800 | D32: Юра за вентиляторы и сварку каркаса в бронницы
A33: 43156 | C33: 3614 | D33: зенкер, цековка, болтишки
A34: 43157 | C34: 1600 | D34: сверло 5,5, метчики М3 и М4.
B35: 1500 | D35: аванс за кроны для полок
A36: 43158 | C36: 15000 | D36: Милколенточка
A37: 43159 | C37: 3000 | D37: Епсон
A38: 43161 | C38: 1000 | D38: подварка ступицы квадра
A39: 43162 | C39: 312 | D39: металл на кроны для полок
A40: 43163 | B40: 3500 | D40: проточка шаровых
B41: 2500 | D41: остаток за кронштейны полок
A42: 43165 | B42: 5000 | D42: аванс за текстолит
A43: 43167 | C43: 14000 | D43: пневмололоток
A44: 43172 | C44: 4310 | D44: милкофонарь и милкоаккумы
B45: 5000 | D45: фторопласт для Терлы
C46: 4700 | D46: Тиски, фрезы
C47: 1750 | D47: фрезы с директлота
A48: 43174 | C48: 3200 | D48: фрезы Олмитул
A49: 43176 | C49: 6000 | D49: поворотный стол
A50: 43180 | B50: 60000 | D50: за текстолит
C51: 4200 | D51: налог за ИП
A52: 43185 | C52: 2300 | D52: переменка по Мануфактуре
C53: 9300 | D53: шпиндель метабо
A54: 43188 | B54: 9300 | D54: шпиндель метабо вернул
A55: 43193 | C55: 1600 | D55: резцы
A56: 43195 | C56: 2500 | D56: ленты для джета
A57: 43196 | B57: 5000 | D57: аванс за проект по стойке для камеры
A58: 43197 | C58: 2000 | D58: фрезы дисковые много.
C59: 1200 | D59: очечи милвоке
C60: 1200 | D60: шлифленты
A61: 43201 | B61: 2500 | D61: сварка самоката
B62: 5000 | D62: аванс за кронштейны для оргстекла и светиков.
A63: 43203 | B63: 1200 | D63: продал остатки текстолита
A64: 43209 | B64: 5000 | D64: за фрезеровку дюрали для ЧПУшки
C65: 3520 | D65: коронки Милвоки
A66: 43214 | B66: 6000 | D66: кроны для оргстекла и светиков
B67: 5000 | D67: ост за проектирование стоек для камеры
B68: 2000 | D68: муфта под подшипник
A69: 43215 | C69: 4300 | D69: свёрла и фрезы ИНПО
B70: 6250 | D70: монтаж Максу в сервисе
A71: 43218 | B71: 9200 | D71: аванс за мангал.
A72: 43226 | B72: 70000 | D72: сорокин отдал за токарник (30 должен)
C73: 8000 | D73: перевозка токарника
A74: 43227 | C74: 38500 | D74: сварочник
A75: 43229 | C75: 1200 | D75: металл на подставку для конусов морзе
A76: 42134 | C76: 4700 | D76: парковка и переменка за апрель
B77: 13000 | D77: продажа сварочника
A78: 42136 | B78: 3000 | D78: сварка блока Вольвы
A79: 42137 | B79: 10000 | D79: сварка поленницы
C80: 3953 | D80: железки для поленницы и себе
A81: 43234 | C81: 1500 | D81: обмен сварочная смесь
C82: 1935 | D82: металл для стойки камеры
C83: 510 | D83: краска для поленинцы
C84: 150 | D84: валики для поленницы
B85: 20000 | D85: аванс за стойку камеры
A86: 43235 | C86: 740 | D86: капролон
C87: 820 | D87: провода и разъёмы
C88: 450 | D88: колёсики
C89: 20832 | D89: шпиндель новый
A90: 43245 | C90: 3700 | D90: коронки Милвоки
C91: 700 | D91: болты
B92: 3000 | D92: доплата за поленницу
B93: 5000 | D93: аванс за каминный прибор
B94: 1000 | D94: сварка какой-то хреновины для мотика
A95: 43252 | C95: 2500 | D95: покраска стойки
C96: 500 | D96: металл в Метэкс
C97: 400 | D97: килограмм порошковки
A98: 43253 | C98: 3000 | D98: металл на каминный прибор
C99: 700 | D99: метизы на каминный прибор и стойку
B100: 2000 | D100: от Макса за сварку радиатора
...

Sheet Лист1
A1: год | B1: приход | C1: расход | D1: доход
A2: 2018 | B2: ='18'!B2 -> 1031550 | C2: ='18'!C2 -> 535506 | D2: =B2-C2 -> 496044
A3: 2019 | B3: ='19'!B2 -> 3540824 | C3: ='19'!C2 -> 1839484 | D3: =B3-C3 -> 1701340
A4: 2020 | B4: ='20'!B2 -> 3509497 | C4: ='20'!C2 -> 1735936.4 | D4: =B4-C4 -> 1773560.6
A5: 2021 | B5: ='21'!B2 -> 4818296 | C5: ='21'!C2 -> 2491250.8 | D5: =B5-C5 -> 2327045.2
A6: 2022 | B6: ='22'!B2 -> 10224884 | C6: ='22'!C2 -> 6327440.5 | D6: =B6-C6 -> 3897443.1
